okx_api/__init__.py
okx_api/_client.py
okx_api/account.py
okx_api/convert.py
okx_api/copytrading.py
okx_api/funding.py
okx_api/grid.py
okx_api/market.py
okx_api/public.py
okx_api/rubik.py
okx_api/staking.py
okx_api/subaccount.py
okx_api/system.py
okx_api/trade.py
okx_api-1.0.5.dist-info/METADATA
okx_api-1.0.5.dist-info/WHEEL
okx_api-1.0.5.dist-info/top_level.txt
okx_api-1.0.5.dist-info/RECORD
